alquimista.py
alquimista-0.1.0.dist-info/LICENSE
alquimista-0.1.0.dist-info/WHEEL
alquimista-0.1.0.dist-info/METADATA
alquimista-0.1.0.dist-info/RECORD
