Metadata-Version: 2.1
Name: alquimista
Version: 0.1.0
Summary: # Alquimista 
Home-page: https://github.com/sashakile/alquimista
License: UNKNOWN
Author: sashakile
Author-email: saxa.kile@gmail.com
Classifier: License :: OSI Approved :: GNU General Public License v3 or later (GPLv3+)
